{
"test/and_convolution.test.cpp": "2021-11-03 19:13:26 +0900",
"test/auto_memoize.test.cpp": "2021-11-03 19:13:26 +0900",
"test/berlekamp_massey.test.cpp": "2021-11-04 19:10:29 +0900",
"test/bipartite_matching.test.cpp": "2021-11-03 19:13:26 +0900",
"test/convolution_arbitrary_mod.test.cpp": "2021-11-03 19:15:27 +0900",
"test/convolution_mod.test.cpp": "2021-11-03 19:13:26 +0900",
"test/dual_segment_tree.test.cpp": "2021-09-27 22:23:01 +0900",
"test/example.test.cpp": "2021-03-31 11:13:07 +0900",
"test/factorize.test.cpp": "2021-09-08 18:46:15 +0900",
"test/fast_io.test.cpp": "2021-11-04 19:10:29 +0900",
"test/fenwick_tree.test.cpp": "2021-09-08 18:46:15 +0900",
"test/heavy_light_decomposition.test.cpp": "2021-11-03 19:13:26 +0900",
"test/integer_hash_table.test.cpp": "2021-10-23 19:56:59 +0900",
"test/integer_hash_table_verbose.test.cpp": "2021-10-23 19:56:59 +0900",
"test/larsch.test.cpp": "2021-11-01 18:27:47 +0900",
"test/lazy_segment_tree.test.cpp": "2021-11-03 19:13:26 +0900",
"test/modint_util.test.cpp": "2021-11-03 19:13:26 +0900",
"test/polynomial_hash.test.cpp": "2021-11-03 19:13:26 +0900",
"test/primal_dual_maxflow.test.cpp": "2021-11-01 18:27:47 +0900",
"test/primal_dual_mincostflow.test.cpp": "2021-11-01 18:27:47 +0900",
"test/prime_sieve.test.cpp": "2021-11-03 19:13:26 +0900",
"test/queue_aggregation.test.cpp": "2021-11-03 19:13:26 +0900",
"test/rollback_union_find.test.cpp": "2021-11-03 19:13:26 +0900",
"test/segment_tree.test.cpp": "2021-11-03 19:13:26 +0900",
"test/segment_tree_beats.test.cpp": "2021-11-04 19:10:29 +0900",
"test/semiring_matrix.test.cpp": "2021-11-03 19:13:26 +0900",
"test/sparse_table.test.cpp": "2021-11-04 19:10:29 +0900",
"test/strongly_connected_components.test.cpp": "2021-11-03 19:13:26 +0900",
"test/totient.test.cpp": "2021-09-08 18:46:15 +0900",
"test/union_find.test.cpp": "2021-09-08 18:46:15 +0900",
"test/z_algorithm.test.cpp": "2021-10-04 09:51:31 +0900"
}